appscriptz/__init__.py
appscriptz/core.py
appscriptz/log.py
appscriptz-1.0.6.dist-info/METADATA
appscriptz-1.0.6.dist-info/WHEEL
appscriptz-1.0.6.dist-info/top_level.txt
appscriptz-1.0.6.dist-info/RECORD
