Metadata-Version: 2.4
Name: appscriptz
Version: 1.0.6
Summary: Add your description here
Requires-Python: >=3.10
Requires-Dist: llama-index==0.12.30
Requires-Dist: llmada==1.0.3
Requires-Dist: promptlibz==1.0.2
Requires-Dist: pytest>=8.3.5
Requires-Dist: toml==0.10.2
